{"1":{"Wife_number":0,"house":1,"hero":1,"id":1,"levelup":1},"2":{"Wife_number":0,"house":1,"hero":2,"id":2,"levelup":2},"7":{"Wife_number":0,"house":2,"hero":2,"id":7,"levelup":3},"12":{"Wife_number":1,"house":2,"hero":2,"id":12,"levelup":4},"17":{"Wife_number":1,"house":2,"hero":3,"id":17,"levelup":5},"24":{"Wife_number":1,"house":3,"hero":3,"id":24,"levelup":6},"33":{"Wife_number":2,"house":3,"hero":3,"id":33,"levelup":7},"45":{"Wife_number":2,"house":3,"hero":4,"id":45,"levelup":8},"61":{"Wife_number":2,"house":4,"hero":4,"id":61,"levelup":9},"81":{"Wife_number":3,"house":4,"hero":4,"id":81,"levelup":10},"101":{"Wife_number":3,"house":4,"hero":5,"id":101,"levelup":11},"121":{"Wife_number":3,"house":5,"hero":5,"id":121,"levelup":12},"141":{"Wife_number":4,"house":5,"hero":5,"id":141,"levelup":13},"161":{"Wife_number":4,"house":5,"hero":6,"id":161,"levelup":14},"181":{"Wife_number":4,"house":6,"hero":6,"id":181,"levelup":15},"201":{"Wife_number":5,"house":6,"hero":6,"id":201,"levelup":16},"221":{"Wife_number":5,"house":6,"hero":7,"id":221,"levelup":17},"241":{"Wife_number":5,"house":7,"hero":7,"id":241,"levelup":18},"261":{"Wife_number":6,"house":7,"hero":7,"id":261,"levelup":19},"281":{"Wife_number":6,"house":7,"hero":8,"id":281,"levelup":20},"301":{"Wife_number":6,"house":8,"hero":8,"id":301,"levelup":21},"321":{"Wife_number":7,"house":8,"hero":8,"id":321,"levelup":22},"341":{"Wife_number":7,"house":8,"hero":9,"id":341,"levelup":23},"361":{"Wife_number":7,"house":9,"hero":9,"id":361,"levelup":24},"381":{"Wife_number":8,"house":9,"hero":9,"id":381,"levelup":25},"401":{"Wife_number":8,"house":9,"hero":10,"id":401,"levelup":26},"421":{"Wife_number":8,"house":10,"hero":10,"id":421,"levelup":27},"441":{"Wife_number":9,"house":10,"hero":10,"id":441,"levelup":28},"461":{"Wife_number":9,"house":10,"hero":11,"id":461,"levelup":29},"481":{"Wife_number":9,"house":11,"hero":11,"id":481,"levelup":30},"501":{"Wife_number":10,"house":11,"hero":11,"id":501,"levelup":31},"521":{"Wife_number":10,"house":11,"hero":12,"id":521,"levelup":32},"541":{"Wife_number":10,"house":12,"hero":12,"id":541,"levelup":33},"561":{"Wife_number":11,"house":12,"hero":12,"id":561,"levelup":34},"581":{"Wife_number":11,"house":12,"hero":13,"id":581,"levelup":35},"601":{"Wife_number":11,"house":13,"hero":13,"id":601,"levelup":36},"621":{"Wife_number":12,"house":13,"hero":13,"id":621,"levelup":37},"641":{"Wife_number":12,"house":13,"hero":14,"id":641,"levelup":38},"661":{"Wife_number":12,"house":14,"hero":14,"id":661,"levelup":39},"681":{"Wife_number":13,"house":14,"hero":14,"id":681,"levelup":40},"701":{"Wife_number":13,"house":14,"hero":15,"id":701,"levelup":41},"721":{"Wife_number":13,"house":15,"hero":15,"id":721,"levelup":42},"741":{"Wife_number":14,"house":15,"hero":15,"id":741,"levelup":43},"761":{"Wife_number":14,"house":15,"hero":16,"id":761,"levelup":44},"781":{"Wife_number":14,"house":16,"hero":16,"id":781,"levelup":45},"801":{"Wife_number":15,"house":16,"hero":16,"id":801,"levelup":46},"821":{"Wife_number":15,"house":16,"hero":17,"id":821,"levelup":47},"841":{"Wife_number":15,"house":17,"hero":17,"id":841,"levelup":48},"861":{"Wife_number":16,"house":17,"hero":17,"id":861,"levelup":49},"881":{"Wife_number":16,"house":17,"hero":18,"id":881,"levelup":50},"901":{"Wife_number":16,"house":18,"hero":18,"id":901,"levelup":51},"921":{"Wife_number":17,"house":18,"hero":18,"id":921,"levelup":52},"941":{"Wife_number":17,"house":18,"hero":19,"id":941,"levelup":53},"961":{"Wife_number":17,"house":19,"hero":19,"id":961,"levelup":54},"981":{"Wife_number":18,"house":19,"hero":19,"id":981,"levelup":55},"1001":{"Wife_number":18,"house":19,"hero":20,"id":1001,"levelup":56},"1021":{"Wife_number":19,"house":19,"hero":20,"id":1021,"levelup":57},"1041":{"Wife_number":19,"house":20,"hero":20,"id":1041,"levelup":58},"1061":{"Wife_number":20,"house":20,"hero":20,"id":1061,"levelup":59},"1081":{"Wife_number":20,"house":20,"hero":21,"id":1081,"levelup":60},"1101":{"Wife_number":21,"house":20,"hero":21,"id":1101,"levelup":61},"1121":{"Wife_number":21,"house":21,"hero":21,"id":1121,"levelup":62},"1141":{"Wife_number":22,"house":21,"hero":21,"id":1141,"levelup":63},"1161":{"Wife_number":22,"house":21,"hero":22,"id":1161,"levelup":64},"1181":{"Wife_number":23,"house":21,"hero":22,"id":1181,"levelup":65},"1201":{"Wife_number":23,"house":22,"hero":22,"id":1201,"levelup":66},"1221":{"Wife_number":24,"house":22,"hero":22,"id":1221,"levelup":67},"1241":{"Wife_number":24,"house":22,"hero":23,"id":1241,"levelup":68},"1261":{"Wife_number":25,"house":22,"hero":23,"id":1261,"levelup":69},"1281":{"Wife_number":25,"house":23,"hero":23,"id":1281,"levelup":70},"1301":{"Wife_number":26,"house":23,"hero":23,"id":1301,"levelup":71},"1321":{"Wife_number":26,"house":23,"hero":24,"id":1321,"levelup":72},"1341":{"Wife_number":27,"house":23,"hero":24,"id":1341,"levelup":73},"1361":{"Wife_number":28,"house":23,"hero":24,"id":1361,"levelup":74},"1381":{"Wife_number":29,"house":23,"hero":24,"id":1381,"levelup":75},"1401":{"Wife_number":30,"house":23,"hero":24,"id":1401,"levelup":76},"1421":{"Wife_number":31,"house":23,"hero":24,"id":1421,"levelup":77},"1441":{"Wife_number":32,"house":23,"hero":24,"id":1441,"levelup":78},"1461":{"Wife_number":33,"house":23,"hero":24,"id":1461,"levelup":79},"1481":{"Wife_number":33,"house":24,"hero":24,"id":1481,"levelup":80},"1501":{"Wife_number":34,"house":24,"hero":24,"id":1501,"levelup":81},"1521":{"Wife_number":34,"house":24,"hero":25,"id":1521,"levelup":82},"1541":{"Wife_number":35,"house":24,"hero":25,"id":1541,"levelup":83},"1561":{"Wife_number":36,"house":24,"hero":25,"id":1561,"levelup":84},"1581":{"Wife_number":37,"house":24,"hero":25,"id":1581,"levelup":85},"1601":{"Wife_number":38,"house":24,"hero":25,"id":1601,"levelup":86},"1621":{"Wife_number":39,"house":24,"hero":25,"id":1621,"levelup":87},"1641":{"Wife_number":40,"house":24,"hero":25,"id":1641,"levelup":88},"1661":{"Wife_number":41,"house":24,"hero":25,"id":1661,"levelup":89},"1681":{"Wife_number":41,"house":25,"hero":25,"id":1681,"levelup":90},"1701":{"Wife_number":42,"house":25,"hero":25,"id":1701,"levelup":91},"1721":{"Wife_number":42,"house":25,"hero":26,"id":1721,"levelup":92},"1741":{"Wife_number":43,"house":25,"hero":26,"id":1741,"levelup":93},"1761":{"Wife_number":44,"house":25,"hero":26,"id":1761,"levelup":94},"1781":{"Wife_number":45,"house":25,"hero":26,"id":1781,"levelup":95},"1801":{"Wife_number":46,"house":25,"hero":26,"id":1801,"levelup":96},"1821":{"Wife_number":47,"house":25,"hero":26,"id":1821,"levelup":97},"1841":{"Wife_number":48,"house":25,"hero":26,"id":1841,"levelup":98},"1861":{"Wife_number":49,"house":25,"hero":26,"id":1861,"levelup":99},"1881":{"Wife_number":49,"house":26,"hero":26,"id":1881,"levelup":100},"1901":{"Wife_number":50,"house":26,"hero":26,"id":1901,"levelup":101},"1921":{"Wife_number":50,"house":26,"hero":27,"id":1921,"levelup":102},"1941":{"Wife_number":51,"house":26,"hero":27,"id":1941,"levelup":103},"1961":{"Wife_number":52,"house":26,"hero":27,"id":1961,"levelup":104},"1981":{"Wife_number":53,"house":26,"hero":27,"id":1981,"levelup":105},"2001":{"Wife_number":54,"house":26,"hero":27,"id":2001,"levelup":106},"2021":{"Wife_number":55,"house":26,"hero":27,"id":2021,"levelup":107},"2041":{"Wife_number":56,"house":26,"hero":27,"id":2041,"levelup":108},"2061":{"Wife_number":57,"house":26,"hero":27,"id":2061,"levelup":109},"2081":{"Wife_number":57,"house":27,"hero":27,"id":2081,"levelup":110},"2101":{"Wife_number":58,"house":27,"hero":27,"id":2101,"levelup":111},"2121":{"Wife_number":58,"house":27,"hero":28,"id":2121,"levelup":112},"2141":{"Wife_number":59,"house":27,"hero":28,"id":2141,"levelup":113},"2161":{"Wife_number":60,"house":27,"hero":28,"id":2161,"levelup":114},"2181":{"Wife_number":61,"house":27,"hero":28,"id":2181,"levelup":115},"2201":{"Wife_number":62,"house":27,"hero":28,"id":2201,"levelup":116},"2221":{"Wife_number":63,"house":27,"hero":28,"id":2221,"levelup":117},"2241":{"Wife_number":64,"house":27,"hero":28,"id":2241,"levelup":118},"2261":{"Wife_number":65,"house":27,"hero":28,"id":2261,"levelup":119},"2281":{"Wife_number":65,"house":28,"hero":28,"id":2281,"levelup":120},"2301":{"Wife_number":66,"house":28,"hero":28,"id":2301,"levelup":121},"2321":{"Wife_number":66,"house":28,"hero":29,"id":2321,"levelup":122},"2341":{"Wife_number":67,"house":28,"hero":29,"id":2341,"levelup":123},"2361":{"Wife_number":68,"house":28,"hero":29,"id":2361,"levelup":124},"2381":{"Wife_number":69,"house":28,"hero":29,"id":2381,"levelup":125},"2401":{"Wife_number":70,"house":28,"hero":29,"id":2401,"levelup":126},"2421":{"Wife_number":71,"house":28,"hero":29,"id":2421,"levelup":127},"2441":{"Wife_number":72,"house":28,"hero":29,"id":2441,"levelup":128},"2461":{"Wife_number":73,"house":28,"hero":29,"id":2461,"levelup":129},"2481":{"Wife_number":73,"house":29,"hero":29,"id":2481,"levelup":130},"2501":{"Wife_number":74,"house":29,"hero":29,"id":2501,"levelup":131},"2521":{"Wife_number":74,"house":29,"hero":30,"id":2521,"levelup":132},"2541":{"Wife_number":75,"house":29,"hero":30,"id":2541,"levelup":133},"2561":{"Wife_number":76,"house":29,"hero":30,"id":2561,"levelup":134},"2581":{"Wife_number":77,"house":29,"hero":30,"id":2581,"levelup":135},"2601":{"Wife_number":78,"house":29,"hero":30,"id":2601,"levelup":136},"2621":{"Wife_number":79,"house":29,"hero":30,"id":2621,"levelup":137},"2641":{"Wife_number":80,"house":29,"hero":30,"id":2641,"levelup":138},"2661":{"Wife_number":81,"house":29,"hero":30,"id":2661,"levelup":139},"2681":{"Wife_number":82,"house":29,"hero":30,"id":2681,"levelup":140},"2701":{"Wife_number":83,"house":29,"hero":30,"id":2701,"levelup":141},"2721":{"Wife_number":84,"house":29,"hero":30,"id":2721,"levelup":142},"2741":{"Wife_number":85,"house":29,"hero":30,"id":2741,"levelup":143},"2761":{"Wife_number":86,"house":29,"hero":30,"id":2761,"levelup":144},"2781":{"Wife_number":87,"house":29,"hero":30,"id":2781,"levelup":145},"2801":{"Wife_number":88,"house":29,"hero":30,"id":2801,"levelup":146},"2821":{"Wife_number":89,"house":29,"hero":30,"id":2821,"levelup":147},"2841":{"Wife_number":90,"house":29,"hero":30,"id":2841,"levelup":148},"2861":{"Wife_number":91,"house":29,"hero":30,"id":2861,"levelup":149},"2881":{"Wife_number":92,"house":29,"hero":30,"id":2881,"levelup":150},"2901":{"Wife_number":93,"house":29,"hero":30,"id":2901,"levelup":151},"2921":{"Wife_number":94,"house":29,"hero":30,"id":2921,"levelup":152},"2941":{"Wife_number":95,"house":29,"hero":30,"id":2941,"levelup":153},"2961":{"Wife_number":96,"house":29,"hero":30,"id":2961,"levelup":154},"2981":{"Wife_number":97,"house":29,"hero":30,"id":2981,"levelup":155},"3001":{"Wife_number":98,"house":29,"hero":30,"id":3001,"levelup":156},"3021":{"Wife_number":99,"house":29,"hero":30,"id":3021,"levelup":157},"3041":{"Wife_number":100,"house":29,"hero":30,"id":3041,"levelup":158},"3061":{"Wife_number":101,"house":29,"hero":30,"id":3061,"levelup":159},"3081":{"Wife_number":102,"house":29,"hero":30,"id":3081,"levelup":160},"3101":{"Wife_number":103,"house":29,"hero":30,"id":3101,"levelup":161},"3121":{"Wife_number":104,"house":29,"hero":30,"id":3121,"levelup":162},"3141":{"Wife_number":105,"house":29,"hero":30,"id":3141,"levelup":163},"3161":{"Wife_number":106,"house":29,"hero":30,"id":3161,"levelup":164},"3181":{"Wife_number":107,"house":29,"hero":30,"id":3181,"levelup":165},"3201":{"Wife_number":108,"house":29,"hero":30,"id":3201,"levelup":166},"3221":{"Wife_number":109,"house":29,"hero":30,"id":3221,"levelup":167},"3241":{"Wife_number":110,"house":29,"hero":30,"id":3241,"levelup":168},"3261":{"Wife_number":111,"house":29,"hero":30,"id":3261,"levelup":169},"3281":{"Wife_number":112,"house":29,"hero":30,"id":3281,"levelup":170},"3301":{"Wife_number":113,"house":29,"hero":30,"id":3301,"levelup":171},"3321":{"Wife_number":114,"house":29,"hero":30,"id":3321,"levelup":172},"3341":{"Wife_number":115,"house":29,"hero":30,"id":3341,"levelup":173},"3361":{"Wife_number":116,"house":29,"hero":30,"id":3361,"levelup":174},"3381":{"Wife_number":117,"house":29,"hero":30,"id":3381,"levelup":175},"3401":{"Wife_number":118,"house":29,"hero":30,"id":3401,"levelup":176},"3421":{"Wife_number":119,"house":29,"hero":30,"id":3421,"levelup":177},"3441":{"Wife_number":120,"house":29,"hero":30,"id":3441,"levelup":178},"3461":{"Wife_number":121,"house":29,"hero":30,"id":3461,"levelup":179},"3481":{"Wife_number":122,"house":29,"hero":30,"id":3481,"levelup":180},"3501":{"Wife_number":123,"house":29,"hero":30,"id":3501,"levelup":181},"3521":{"Wife_number":124,"house":29,"hero":30,"id":3521,"levelup":182},"3541":{"Wife_number":125,"house":29,"hero":30,"id":3541,"levelup":183},"3561":{"Wife_number":126,"house":29,"hero":30,"id":3561,"levelup":184},"3581":{"Wife_number":127,"house":29,"hero":30,"id":3581,"levelup":185},"3601":{"Wife_number":128,"house":29,"hero":30,"id":3601,"levelup":186},"3621":{"Wife_number":129,"house":29,"hero":30,"id":3621,"levelup":187},"3641":{"Wife_number":130,"house":29,"hero":30,"id":3641,"levelup":188},"3661":{"Wife_number":131,"house":29,"hero":30,"id":3661,"levelup":189},"3681":{"Wife_number":132,"house":29,"hero":30,"id":3681,"levelup":190},"3701":{"Wife_number":133,"house":29,"hero":30,"id":3701,"levelup":191},"3721":{"Wife_number":134,"house":29,"hero":30,"id":3721,"levelup":192},"3741":{"Wife_number":135,"house":29,"hero":30,"id":3741,"levelup":193},"3761":{"Wife_number":136,"house":29,"hero":30,"id":3761,"levelup":194},"3781":{"Wife_number":137,"house":29,"hero":30,"id":3781,"levelup":195},"3801":{"Wife_number":138,"house":29,"hero":30,"id":3801,"levelup":196},"3821":{"Wife_number":139,"house":29,"hero":30,"id":3821,"levelup":197},"3841":{"Wife_number":140,"house":29,"hero":30,"id":3841,"levelup":198},"3861":{"Wife_number":141,"house":29,"hero":30,"id":3861,"levelup":199},"3881":{"Wife_number":142,"house":29,"hero":30,"id":3881,"levelup":200},"3901":{"Wife_number":143,"house":29,"hero":30,"id":3901,"levelup":201},"3921":{"Wife_number":144,"house":29,"hero":30,"id":3921,"levelup":202},"3941":{"Wife_number":145,"house":29,"hero":30,"id":3941,"levelup":203},"3961":{"Wife_number":146,"house":29,"hero":30,"id":3961,"levelup":204},"3981":{"Wife_number":147,"house":29,"hero":30,"id":3981,"levelup":205},"4001":{"Wife_number":148,"house":29,"hero":30,"id":4001,"levelup":206}}